MANIFEST.in
README.rst
manage.py
setup.py
console/__init__.py
console/cert.pem
console/tests.py
console/tunnel.py
console/views.py
create/__init__.py
create/forms.py
create/models.py
create/tests.py
create/views.py
create/fixtures/initial_data.json
hostdetail/__init__.py
hostdetail/tests.py
hostdetail/views.py
images/README.md
instance/__init__.py
instance/models.py
instance/tests.py
instance/views.py
instance/templatetags/__init__.py
instance/templatetags/tags_active.py
interfaces/__init__.py
interfaces/forms.py
interfaces/tests.py
interfaces/views.py
locale/da_DK/LC_MESSAGES/django.po
locale/ru/LC_MESSAGES/django.po
locale/zh_CN/LC_MESSAGES/django.po
networks/__init__.py
networks/forms.py
networks/tests.py
networks/views.py
secrets/__init__.py
secrets/forms.py
secrets/tests.py
secrets/views.py
serverlog/__init__.py
serverlog/models.py
serverlog/tests.py
serverlog/views.py
servers/__init__.py
servers/forms.py
servers/models.py
servers/tests.py
servers/views.py
storages/__init__.py
storages/forms.py
storages/tests.py
storages/views.py
templates/404.html
templates/500.html
templates/base.html
templates/base_auth.html
templates/console-spice.html
templates/console-vnc.html
templates/create.html
templates/hostdetail.html
templates/infrastructure.html
templates/instance.html
templates/instances.html
templates/interface.html
templates/interfaces.html
templates/login.html
templates/logout.html
templates/network.html
templates/networks.html
templates/secrets.html
templates/servers.html
templates/sidebar.html
templates/sidebar_close.html
templates/storage.html
templates/storages.html
vrtManager/IPy.py
vrtManager/__init__.py
vrtManager/connection.py
vrtManager/create.py
vrtManager/hostdetails.py
vrtManager/instance.py
vrtManager/interface.py
vrtManager/network.py
vrtManager/rwlock.py
vrtManager/secrets.py
vrtManager/storage.py
vrtManager/util.py
webvirtmgr/__init__.py
webvirtmgr/settings.py
webvirtmgr/settings_jenkins.py
webvirtmgr/urls.py
webvirtmgr/wsgi.py
webvirtmgr.egg-info/PKG-INFO
webvirtmgr.egg-info/SOURCES.txt
webvirtmgr.egg-info/dependency_links.txt
webvirtmgr.egg-info/namespace_packages.txt
webvirtmgr.egg-info/not-zip-safe
webvirtmgr.egg-info/requires.txt
webvirtmgr.egg-info/top_level.txt
