Metadata-Version: 1.0
Name: webvirtmgr
Version: 4.8.9
Summary: WebVirtMgr panel for manage virtual machine
Home-page: http://github.com/retspen/webvirtmgr
Author: Anatoliy Guskov
Author-email: anatoliy.guskov@gmail.com
License: Apache Licence, Version 2.0.
Platform: UNKNOWN
